{"analysisResults":[{"rmsDistanceRatio":0.0006495112992231138},{"rmsDistanceRatio":0.0025206731503712217},{"rmsDistanceRatio":0.0006924726158625828},{"rmsDistanceRatio":0.031228801908890616},{"rmsDistanceRatio":0.0031608215995024744}],"scenario":{"lighting":"../../../shared-assets/environments/lightroom_14b.hdr","dimensions":{"width":400,"height":768},"target":{"x":0,"y":1,"z":0},"orbit":{"theta":0,"phi":90,"radius":2.5},"verticalFoV":45,"renderSkybox":false,"name":"khronos-SimpleSkin","model":"../../../shared-assets/models/glTF-Sample-Assets/Models/SimpleSkin/glTF/SimpleSkin.gltf","exclude":["stellar","three-gpu-pathtracer"]}}