{"analysisResults":[{"rmsDistanceRatio":0.008552364146106517},{"rmsDistanceRatio":0.001286524500824858},{"rmsDistanceRatio":0.0015498569123318419},{"rmsDistanceRatio":0.020505219039938575},{"rmsDistanceRatio":0.011147502631547786},{"rmsDistanceRatio":0.024910520511563058}],"scenario":{"lighting":"../../../shared-assets/environments/lightroom_14b.hdr","dimensions":{"width":768,"height":768},"target":{"x":0,"y":0,"z":0},"orbit":{"theta":0,"phi":90,"radius":11},"verticalFoV":45,"renderSkybox":false,"name":"AlphaBlendLitmusTest","model":"../../../shared-assets/models/alpha-blend-litmus.glb","exclude":["stellar"]}}