{"analysisResults":[{"rmsDistanceRatio":0.005123195030422719},{"rmsDistanceRatio":0.006307612992988066},{"rmsDistanceRatio":0.008876278894103739},{"rmsDistanceRatio":0.011478053022043648},{"rmsDistanceRatio":0.005311802843567826}],"scenario":{"lighting":"../../../shared-assets/environments/lightroom_14b.hdr","dimensions":{"width":768,"height":768},"target":{"x":0,"y":0.5,"z":0},"orbit":{"theta":0,"phi":90,"radius":2},"verticalFoV":45,"renderSkybox":false,"name":"khronos-ClearCoatCarPaint","model":"../../../shared-assets/models/glTF-Sample-Assets/Models/ClearCoatCarPaint/glTF/ClearCoatCarPaint.gltf","exclude":["stellar","vray"]}}