{"analysisResults":[{"rmsDistanceRatio":0.013189193352234261},{"rmsDistanceRatio":0.020872060896440295},{"rmsDistanceRatio":0.07637088004539792},{"rmsDistanceRatio":0.06584994925000598},{"rmsDistanceRatio":0.05934862227074801}],"scenario":{"lighting":"../../../shared-assets/environments/spruit_sunrise_1k_HDR.hdr","dimensions":{"width":768,"height":570},"target":{"x":0,"y":0.11,"z":0},"orbit":{"theta":-70,"phi":90,"radius":0.47},"verticalFoV":45,"renderSkybox":true,"name":"khronos-IridescentDishWithOlives","model":"../../../shared-assets/models/glTF-Sample-Assets/Models/IridescentDishWithOlives/glTF-Binary/IridescentDishWithOlives.glb","exclude":["babylon","vray"]}}